setup.py
amieraser/__init__.py
amieraser/amieraser.py
amieraser.egg-info/PKG-INFO
amieraser.egg-info/SOURCES.txt
amieraser.egg-info/dependency_links.txt
amieraser.egg-info/entry_points.txt
amieraser.egg-info/not-zip-safe
amieraser.egg-info/requires.txt
amieraser.egg-info/top_level.txt