Metadata-Version: 1.0
Name: amieraser
Version: 1.0.0
Summary: Tool to delete Amazon AMIs and associated Snapshots
Home-page: https://github.com/drboyer/AMIEraser
Author: Devin Boyer
Author-email: drb5272@gmail.com
License: MIT
Platform: UNKNOWN
